pu_pjr/__init__.py
pu_pjr/dir_stats/__init__.py
pu_pjr/dir_stats/__main__.py
pu_pjr/dir_stats/dir_contents.py
pu_pjr/dir_stats/utils.py
pu_pjr/force_fields_plotting/__init__.py
pu_pjr/force_fields_plotting/__main__.py
pu_pjr/force_fields_plotting/force_fields.py
pu_pjr/force_fields_plotting/utils.py
pu_pjr/lammps_helper/__init__.py
pu_pjr/plotting/__init__.py
pu_pjr/plotting/__main__.py
pu_pjr/plotting/multi_file.py
pu_pjr/plotting/stats.py
pu_pjr/plotting/utils.py
pu_pjr/plotting/xy.py
pu_pjr-0.20.0.dist-info/METADATA
pu_pjr-0.20.0.dist-info/WHEEL
pu_pjr-0.20.0.dist-info/entry_points.txt
pu_pjr-0.20.0.dist-info/RECORD
