Metadata-Version: 2.1
Name: pu-pjr
Version: 0.20.0
Summary: Personal utilities for coding and data analysis
Home-page: https://github.com/Parzival1918/Personal-Utilities
Author: Pedro Juan Royo
Author-email: pedro.juan.royo@gmail.com
Requires-Python: ==3.11.*
Classifier: Programming Language :: Python :: 3
Classifier: Programming Language :: Python :: 3.11
Requires-Dist: matplotlib (>=3.8.0,<4.0.0)
Requires-Dist: ovito (>=3.9.2,<4.0.0)
Requires-Dist: pandas (>=2.1.1,<3.0.0)
Requires-Dist: rich (>=13.6.0,<14.0.0)
Project-URL: Repository, https://github.com/Parzival1918/Personal-Utilities
